README.md
setup.cfg
setup.py
failfast/__init__.py
failfast/failfast.py
failfast/store.py
failfast.egg-info/PKG-INFO
failfast.egg-info/SOURCES.txt
failfast.egg-info/dependency_links.txt
failfast.egg-info/top_level.txt
failfast/tests/__init__.py
failfast/tests/failfast_tests.py
failfast/tests/linter_tests.py
failfast/tests/store_tests.py