Metadata-Version: 1.1
Name: failfast
Version: 0.0.3
Summary: Pythonic Circuit Breaker
Home-page: https://github.com/ticketea/failfast
Author: Matias Surdi
Author-email: matias@surdi.net
License: UNKNOWN
Keywords: circuitbreaker,circuit,breaker
Platform: any
Classifier: Intended Audience :: Developers
Classifier: Natural Language :: English
Classifier: Operating System :: OS Independent
Classifier: Programming Language :: Python
Classifier: Programming Language :: Python :: 3
